pygerg/__init__.py
pygerg/gerg88.py
pygerg-0.1.0.dist-info/licenses/LICENSE
pygerg-0.1.0.dist-info/METADATA
pygerg-0.1.0.dist-info/WHEEL
pygerg-0.1.0.dist-info/top_level.txt
pygerg-0.1.0.dist-info/RECORD
