Metadata-Version: 2.4
Name: pygerg
Version: 0.1.0
Summary: Python implementation of the GERG-88 standard for natural gas properties
Home-page: https://github.com/safersephy/pygerg
Author: Tijs van der Velden
Author-email: Tijs van der Velden <tijsvdvelden@hotmail.com>
License: MIT
Project-URL: Homepage, https://github.com/safersephy/pygerg
Project-URL: Bug Tracker, https://github.com/safersephy/pygerg/issues
Classifier: Programming Language :: Python :: 3
Classifier: Programming Language :: Python :: 3.7
Classifier: Programming Language :: Python :: 3.8
Classifier: Programming Language :: Python :: 3.9
Classifier: Programming Language :: Python :: 3.10
Classifier: Programming Language :: Python :: 3.11
Classifier: License :: OSI Approved :: MIT License
Classifier: Operating System :: OS Independent
Classifier: Topic :: Scientific/Engineering
Classifier: Topic :: Scientific/Engineering :: Chemistry
Classifier: Topic :: Scientific/Engineering :: Physics
Requires-Python: >=3.7
License-File: LICENSE
Dynamic: author
Dynamic: home-page
Dynamic: license-file
Dynamic: requires-python
